django_attribution/__init__.py
django_attribution/admin.py
django_attribution/apps.py
django_attribution/attribution_models.py
django_attribution/conf.py
django_attribution/decorators.py
django_attribution/middlewares.py
django_attribution/mixins.py
django_attribution/models.py
django_attribution/querysets.py
django_attribution/reconciliation.py
django_attribution/settings.py
django_attribution/shortcuts.py
django_attribution/trackers.py
django_attribution/types.py
django_attribution/migrations/0001_initial.py
django_attribution/migrations/__init__.py
django_attribution-0.1.6.dist-info/METADATA
django_attribution-0.1.6.dist-info/WHEEL
django_attribution-0.1.6.dist-info/RECORD
