Metadata-Version: 2.4
Name: django-attribution
Version: 0.1.6
Summary: Django package for tracking campaign conversions with UTM parameters
Author-email: Younes Oumakhou <younesoumakhousudo@gmail.com>
License: MIT
Keywords: analytics,campaign,conversion,django,tracking,utm
Classifier: Development Status :: 3 - Alpha
Classifier: Framework :: Django
Classifier: Framework :: Django :: 4.2
Classifier: Framework :: Django :: 5.0
Classifier: Framework :: Django :: 5.1
Classifier: Intended Audience :: Developers
Classifier: License :: OSI Approved :: MIT License
Classifier: Natural Language :: English
Classifier: Programming Language :: Python :: 3
Classifier: Programming Language :: Python :: 3.8
Classifier: Programming Language :: Python :: 3.9
Classifier: Programming Language :: Python :: 3.10
Classifier: Programming Language :: Python :: 3.11
Classifier: Programming Language :: Python :: 3.12
Classifier: Topic :: Internet :: WWW/HTTP
Classifier: Topic :: Software Development :: Libraries :: Python Modules
Requires-Python: >=3.8
Requires-Dist: django>=3.2
Provides-Extra: dev
Requires-Dist: django-stubs[compatible-mypy]>=4.2; extra == 'dev'
Requires-Dist: pre-commit>=3.0; extra == 'dev'
Requires-Dist: pytest-cov>=4.0; extra == 'dev'
Requires-Dist: pytest-django>=4.5; extra == 'dev'
Requires-Dist: pytest>=7.0; extra == 'dev'
Requires-Dist: tox>=4.0; extra == 'dev'
